angelcv/__init__.py
angelcv/config/__init__.py
angelcv/config/config_manager.py
angelcv/config/config_registry.py
angelcv/config/general.yaml
angelcv/config/dataset/coco.yaml
angelcv/config/dataset/dataset_example.yaml
angelcv/config/model/yolov10b.yaml
angelcv/config/model/yolov10l.yaml
angelcv/config/model/yolov10m.yaml
angelcv/config/model/yolov10n.yaml
angelcv/config/model/yolov10s.yaml
angelcv/config/model/yolov10x.yaml
angelcv/dataset/augmentation_pipelines.py
angelcv/dataset/coco_datamodule.py
angelcv/dataset/custom_transforms.py
angelcv/dataset/yolo_datamodule.py
angelcv/interface/inference_result.py
angelcv/interface/object_detection.py
angelcv/model/blocks.py
angelcv/model/yolo.py
angelcv/tools/ema.py
angelcv/tools/loss.py
angelcv/tools/tal.py
angelcv/utils/annotation_utils.py
angelcv/utils/block_utils.py
angelcv/utils/env_utils.py
angelcv/utils/logging_manager.py
angelcv/utils/ops_utils.py
angelcv/utils/path_utils.py
angelcv/utils/source_utils.py
angelcv-0.2.0.dist-info/licenses/LICENSE
angelcv-0.2.0.dist-info/METADATA
angelcv-0.2.0.dist-info/WHEEL
angelcv-0.2.0.dist-info/top_level.txt
angelcv-0.2.0.dist-info/RECORD
