Metadata-Version: 2.4
Name: angelcv
Version: 0.2.0
Summary: Train and inference for Computer Vision models made easy.
Author-email: Iu Ayala <iu.ayala@gradientinsight.com>
Maintainer-email: Iu Ayala <iu.ayala@gradientinsight.com>
License: Copyright 2025- Angel Protection Systems Inc.
Keywords: computer-vision,deep-learning,machine-learning,AI,ML,DL,YOLO,YOLOv10,AngelCV
Classifier: Development Status :: 3 - Alpha
Classifier: License :: OSI Approved :: Apache Software License
Classifier: Intended Audience :: Developers
Classifier: Intended Audience :: Science/Research
Classifier: Intended Audience :: Education
Classifier: Topic :: Scientific/Engineering :: Artificial Intelligence
Classifier: Topic :: Scientific/Engineering :: Image Recognition
Classifier: Topic :: Scientific/Engineering :: Image Processing
Classifier: Programming Language :: Python :: 3
Classifier: Programming Language :: Python :: 3.9
Classifier: Programming Language :: Python :: 3.10
Classifier: Programming Language :: Python :: 3.11
Classifier: Programming Language :: Python :: 3.12
Classifier: Programming Language :: Python :: 3 :: Only
Classifier: Operating System :: OS Independent
Requires-Python: <3.13,>=3.9
License-File: LICENSE
Requires-Dist: albumentations>=2.0.4
Requires-Dist: boto3>=1.37.3
Requires-Dist: einops>=0.8.1
Requires-Dist: ema-pytorch>=0.7.7
Requires-Dist: lightning>=2.5.0.post0
Requires-Dist: matplotlib>=3.9.4
Requires-Dist: numpy>=2.0.2
Requires-Dist: omegaconf>=2.3.0
Requires-Dist: onnx>=1.17.0
Requires-Dist: opencv-python>=4.11.0.86
Requires-Dist: pandas>=2.2.3
Requires-Dist: pillow>=11.1.0
Requires-Dist: psutil>=7.0.0
Requires-Dist: py-cpuinfo>=9.0.0
Requires-Dist: pycocotools>=2.0.8
Requires-Dist: pyqt5>=5.15.11
Requires-Dist: pyyaml>=6.0.2
Requires-Dist: requests>=2.32.3
Requires-Dist: rich>=13.9.4
Requires-Dist: scipy>=1.13.1
Requires-Dist: seaborn>=0.13.2
Requires-Dist: tensorboard>=2.19.0
Requires-Dist: torch>=2.6.0
Requires-Dist: torchvision>=0.21.0
Requires-Dist: tqdm>=4.67.1
Dynamic: license-file
